composabl_ray/__init__.cpython-38-x86_64-linux-gnu.so
composabl_ray/skill_demo.cpython-38-x86_64-linux-gnu.so
composabl_ray/training_callbacks.cpython-38-x86_64-linux-gnu.so
composabl_ray/runtime.cpython-38-x86_64-linux-gnu.so
composabl_ray/main.cpython-38-x86_64-linux-gnu.so
composabl_ray/env/env_composabl_selector.cpython-38-x86_64-linux-gnu.so
composabl_ray/env/__init__.cpython-38-x86_64-linux-gnu.so
composabl_ray/env/env_composabl.cpython-38-x86_64-linux-gnu.so
composabl_ray/env/selector_processor.cpython-38-x86_64-linux-gnu.so
composabl_ray/env/env_config.cpython-38-x86_64-linux-gnu.so
composabl_ray/env/env_manager.cpython-38-x86_64-linux-gnu.so
composabl_ray/env/base_skill_processor.cpython-38-x86_64-linux-gnu.so
composabl_ray/sim/sim_local.cpython-38-x86_64-linux-gnu.so
composabl_ray/sim/__init__.cpython-38-x86_64-linux-gnu.so
composabl_ray/sim/sim_docker.cpython-38-x86_64-linux-gnu.so
composabl_ray/sim/sim_kubernetes.cpython-38-x86_64-linux-gnu.so
composabl_ray/sim/sim_strategy.cpython-38-x86_64-linux-gnu.so
composabl_ray/sim/sim_manager.cpython-38-x86_64-linux-gnu.so
composabl_ray/trainer/__init__.cpython-38-x86_64-linux-gnu.so
composabl_ray/trainer/skill_trainer_selector.cpython-38-x86_64-linux-gnu.so
composabl_ray/trainer/skill_trainer.cpython-38-x86_64-linux-gnu.so
composabl_ray/actor/actor.cpython-38-x86_64-linux-gnu.so
composabl_ray/actor/__init__.cpython-38-x86_64-linux-gnu.so
composabl_ray/ray/__init__.cpython-38-x86_64-linux-gnu.so
composabl_ray/ray/skill_model.cpython-38-x86_64-linux-gnu.so
composabl_ray_dev-0.3.5.dist-info/top_level.txt
composabl_ray_dev-0.3.5.dist-info/RECORD
composabl_ray_dev-0.3.5.dist-info/METADATA
composabl_ray_dev-0.3.5.dist-info/WHEEL
