Metadata-Version: 2.1
Name: composabl-ray-dev
Version: 0.3.5
Summary: a distributed runtime to be able to train agents across a cluster of machines
Author-email: Xavier Geerinck <xavier@composabl.io>, Hunter Park <hunter@composabl.io>
Requires-Python: <3.9,>=3.8
Requires-Dist: composabl-core-dev >=0.3.5
Requires-Dist: networkx ==3.1
Requires-Dist: dapr ==1.10.0
Requires-Dist: docker ==6.0.1
Requires-Dist: kubernetes ==26.1.0
Requires-Dist: pytest-asyncio ==0.21.0
Requires-Dist: ray[rllib] ==2.6.3
Requires-Dist: urllib3 ==1.26.12
Requires-Dist: torch ==2.0.0
